auto_round/__init__.py
auto_round/autoround.py
auto_round/export_to_autogptq.py
auto_round/sign_sgd.py
auto_round/utils.py
auto_round/version.py
auto_round/export_to_itrex/__init__.py
auto_round/export_to_itrex/config.py
auto_round/export_to_itrex/export.py
auto_round/export_to_itrex/model_wrapper.py
auto_around-0.0.dist-info/LICENSE
auto_around-0.0.dist-info/METADATA
auto_around-0.0.dist-info/WHEEL
auto_around-0.0.dist-info/third-party-programs.txt
auto_around-0.0.dist-info/top_level.txt
auto_around-0.0.dist-info/RECORD
