Metadata-Version: 2.1
Name: auto-around
Version: 0.0
Summary: Repository of AutoRound: Advanced Weight-Only Quantization Algorithm for LLMs
Home-page: https://github.com/intel/auto-round
Author: Intel AIPT Team
Author-email: wenhua.cheng@intel.com, weiwei1.zhang@intel.com
License: Apache 2.0
Keywords: quantization,auto-around,LLM,SignRound
Classifier: Intended Audience :: Science/Research
Classifier: Programming Language :: Python :: 3
Classifier: Topic :: Scientific/Engineering :: Artificial Intelligence
Classifier: License :: OSI Approved :: Apache Software License
Requires-Python: >=3.7.0
License-File: LICENSE
License-File: third-party-programs.txt
Requires-Dist: transformers ==4.36.0
Requires-Dist: torch ==2.0.1
Requires-Dist: sentencepiece
Requires-Dist: accelerate
Requires-Dist: datasets
